{"events":[{"params":[2],"name":"Camera Movement","time":0},{"params":[2,1],"name":"Camera Modulo Change","time":0},{"params":["whos.eli","whos.eli","terminalangst","resurrectionsolar","4.5"],"time":0,"name":"Credits"},{"params":[0],"name":"Camera Movement","time":9411.76470588235},{"params":[1],"time":14117.6470588235,"name":"Camera Movement"},{"params":[0],"time":18823.5294117647,"name":"Camera Movement"},{"params":[1,"hey",true],"name":"Play Animation","time":18823.5294117647},{"params":[1],"time":23529.4117647059,"name":"Camera Movement"},{"params":[0],"time":28235.2941176471,"name":"Camera Movement"},{"params":[1,1],"name":"Camera Modulo Change","time":28235.2941176471},{"params":[1],"name":"Camera Movement","time":29411.7647058824},{"params":[0],"name":"Camera Movement","time":30588.2352941176},{"params":[1],"name":"Camera Movement","time":31764.7058823529},{"params":[1,"hey",true],"name":"Play Animation","time":32352.9411764706},{"params":[0],"name":"Camera Movement","time":32941.1764705882},{"params":[1],"name":"Camera Movement","time":34117.6470588235},{"params":[0],"name":"Camera Movement","time":35294.1176470588},{"params":[1],"name":"Camera Movement","time":36470.5882352941},{"params":[0],"name":"Camera Movement","time":37647.0588235294},{"params":[1,"hey",false],"name":"Play Animation","time":41764.7058823529},{"params":[1],"name":"Camera Movement","time":41764.7058823529},{"params":[2,1],"name":"Camera Modulo Change","time":47058.8235294118},{"params":[0],"time":56470.5882352941,"name":"Camera Movement"},{"params":[1,1],"name":"Camera Modulo Change","time":56470.5882352941},{"params":[1],"time":64705.8823529412,"name":"Camera Movement"},{"params":[1,"hey",true],"time":65588.2352941177,"name":"Play Animation"},{"params":[2,1],"name":"Camera Modulo Change","time":65882.3529411765},{"params":[0],"time":65882.3529411765,"name":"Camera Movement"},{"params":[1],"time":70588.2352941176,"name":"Camera Movement"},{"params":[0],"time":75294.1176470588,"name":"Camera Movement"},{"params":[1],"time":80000,"name":"Camera Movement"},{"params":[0,"DARNELL??",true],"name":"Play Animation","time":84705.8823529412},{"params":[1,"DARNELL??",true],"name":"Play Animation","time":84705.8823529412},{"params":[0],"name":"Camera Movement","time":86470.5882352941},{"params":[2],"name":"Camera Movement","time":88235.2941176471}],"scrollSpeed":2.8,"codenameChart":true,"strumLines":[{"notes":[{"id":1,"sLen":0,"time":9705.88235294118,"type":0},{"id":2,"sLen":0,"time":9852.94117647059,"type":0},{"id":3,"sLen":0,"time":10000,"type":0},{"id":0,"sLen":0,"time":10147.0588235294,"type":0},{"id":2,"sLen":0,"time":10294.1176470588,"type":0},{"id":1,"sLen":0,"time":10441.1764705882,"type":0},{"id":2,"sLen":0,"time":10588.2352941176,"type":0},{"id":3,"sLen":0,"time":10735.2941176471,"type":0},{"id":1,"sLen":0,"time":10882.3529411765,"type":0},{"id":2,"sLen":0,"time":11029.4117647059,"type":0},{"id":1,"sLen":0,"time":11176.4705882353,"type":0},{"id":0,"sLen":0,"time":11323.5294117647,"type":0},{"id":1,"sLen":0,"time":11470.5882352941,"type":0},{"id":2,"sLen":148,"time":11470.5882352941,"type":0},{"id":3,"sLen":0,"time":12058.8235294118,"type":0},{"id":1,"sLen":0,"time":12205.8823529412,"type":0},{"id":0,"sLen":0,"time":12352.9411764706,"type":0},{"id":2,"sLen":0,"time":12500,"type":0},{"id":1,"sLen":0,"time":12647.0588235294,"type":0},{"id":2,"sLen":0,"time":12794.1176470588,"type":0},{"id":3,"sLen":0,"time":12941.1764705882,"type":0},{"id":2,"sLen":0,"time":13088.2352941176,"type":0},{"id":1,"sLen":0,"time":13235.2941176471,"type":0},{"id":2,"sLen":0,"time":13382.3529411765,"type":0},{"id":0,"sLen":0,"time":13529.4117647059,"type":0},{"id":3,"sLen":0,"time":13676.4705882353,"type":0},{"id":1,"sLen":0,"time":13823.5294117647,"type":0},{"id":2,"sLen":0,"time":13970.5882352941,"type":0},{"id":0,"sLen":148,"time":14117.6470588235,"type":0},{"id":3,"sLen":0,"time":19117.6470588235,"type":0},{"id":0,"sLen":0,"time":19264.7058823529,"type":0},{"id":2,"sLen":0,"time":19411.7647058823,"type":0},{"id":3,"sLen":0,"time":19411.7647058823,"type":0},{"id":1,"sLen":297,"time":19705.8823529412,"type":0},{"id":2,"sLen":0,"time":20294.1176470588,"type":0},{"id":1,"sLen":0,"time":20441.1764705882,"type":0},{"id":3,"sLen":0,"time":20588.2352941176,"type":0},{"id":1,"sLen":0,"time":20735.2941176471,"type":0},{"id":0,"sLen":444,"time":20882.3529411765,"type":0},{"id":2,"sLen":0,"time":21470.5882352941,"type":0},{"id":1,"sLen":0,"time":21617.6470588235,"type":0},{"id":3,"sLen":0,"time":21764.7058823529,"type":0},{"id":3,"sLen":296,"time":22058.8235294118,"type":0},{"id":2,"sLen":0,"time":22647.0588235294,"type":0},{"id":1,"sLen":0,"time":22794.1176470588,"type":0},{"id":0,"sLen":0,"time":22941.1764705882,"type":0},{"id":0,"sLen":0,"time":23088.2352941176,"type":0},{"id":3,"sLen":444,"time":23235.2941176471,"type":0},{"id":2,"sLen":0,"time":28235.2941176471,"type":0},{"id":1,"sLen":0,"time":28382.3529411765,"type":0},{"id":2,"sLen":0,"time":28529.4117647059,"type":0},{"id":1,"sLen":0,"time":28676.4705882353,"type":0},{"id":2,"sLen":0,"time":29117.6470588235,"type":0},{"id":2,"sLen":0,"time":29264.7058823529,"type":0},{"id":2,"sLen":0,"time":30588.2352941176,"type":0},{"id":1,"sLen":0,"time":30735.2941176471,"type":0},{"id":0,"sLen":0,"time":30882.3529411765,"type":0},{"id":2,"sLen":0,"time":31029.4117647059,"type":0},{"id":1,"sLen":0,"time":31176.4705882353,"type":0},{"id":3,"sLen":0,"time":31323.5294117647,"type":0},{"id":2,"sLen":0,"time":32941.1764705882,"type":0},{"id":1,"sLen":0,"time":33088.2352941176,"type":0},{"id":3,"sLen":0,"time":33235.2941176471,"type":0},{"id":1,"sLen":0,"time":33382.3529411765,"type":0},{"id":2,"sLen":0,"time":33529.4117647059,"type":0},{"id":0,"sLen":0,"time":33676.4705882353,"type":0},{"id":1,"sLen":0,"time":33823.5294117647,"type":0},{"id":2,"sLen":0,"time":35294.1176470588,"type":0},{"id":1,"sLen":0,"time":35441.1764705882,"type":0},{"id":2,"sLen":0,"time":35588.2352941176,"type":0},{"id":1,"sLen":0,"time":35735.2941176471,"type":0},{"id":3,"sLen":0,"time":35882.3529411765,"type":0},{"id":0,"sLen":0,"time":36029.4117647059,"type":0},{"id":3,"sLen":0,"time":37941.1764705882,"type":0},{"id":1,"sLen":0,"time":38529.4117647059,"type":0},{"id":1,"sLen":0,"time":38676.4705882353,"type":0},{"id":0,"sLen":0,"time":38823.5294117647,"type":0},{"id":2,"sLen":0,"time":38970.5882352941,"type":0},{"id":3,"sLen":0,"time":39117.6470588235,"type":0},{"id":1,"sLen":0,"time":39264.7058823529,"type":0},{"id":0,"sLen":0,"time":39411.7647058823,"type":0},{"id":2,"sLen":0,"time":39558.8235294118,"type":0},{"id":1,"sLen":0,"time":39705.8823529412,"type":0},{"id":3,"sLen":0,"time":39852.9411764706,"type":0},{"id":2,"sLen":148,"time":40000,"type":0},{"id":0,"sLen":0,"time":40294.1176470588,"type":0},{"id":2,"sLen":0,"time":40441.1764705882,"type":0},{"id":3,"sLen":0,"time":40588.2352941176,"type":0},{"id":1,"sLen":0,"time":40735.294117647,"type":0},{"id":2,"sLen":0,"time":40882.3529411765,"type":0},{"id":0,"sLen":0,"time":41029.4117647059,"type":0},{"id":1,"sLen":148,"time":41176.4705882353,"type":0},{"id":2,"sLen":0,"time":41470.5882352941,"type":0},{"id":1,"sLen":0,"time":41617.6470588235,"type":0},{"id":3,"sLen":0,"time":41764.7058823529,"type":0},{"id":1,"sLen":0,"time":41911.7647058823,"type":0},{"id":0,"sLen":0,"time":42058.8235294118,"type":0},{"id":2,"sLen":0,"time":42205.8823529412,"type":0},{"id":2,"sLen":0,"time":56470.5882352941,"type":0},{"id":2,"sLen":0,"time":56617.6470588235,"type":0},{"id":1,"sLen":0,"time":56764.7058823529,"type":0},{"id":3,"sLen":148,"time":56911.7647058823,"type":0},{"id":2,"sLen":0,"time":57205.8823529412,"type":0},{"id":0,"sLen":0,"time":57352.9411764706,"type":0},{"id":1,"sLen":0,"time":57500,"type":0},{"id":3,"sLen":0,"time":57647.0588235294,"type":0},{"id":2,"sLen":0,"time":57794.1176470588,"type":0},{"id":0,"sLen":0,"time":57941.1764705882,"type":0},{"id":1,"sLen":0,"time":58088.2352941176,"type":0},{"id":3,"sLen":0,"time":58235.294117647,"type":0},{"id":2,"sLen":0,"time":58382.3529411765,"type":0},{"id":2,"sLen":0,"time":58529.4117647059,"type":0},{"id":0,"sLen":0,"time":58676.4705882353,"type":0},{"id":3,"sLen":0,"time":58823.5294117647,"type":0},{"id":3,"sLen":0,"time":58970.5882352941,"type":0},{"id":1,"sLen":0,"time":59117.6470588235,"type":0},{"id":2,"sLen":0,"time":59264.7058823529,"type":0},{"id":0,"sLen":0,"time":59411.7647058823,"type":0},{"id":1,"sLen":0,"time":59705.8823529412,"type":0},{"id":2,"sLen":0,"time":59852.9411764706,"type":0},{"id":3,"sLen":0,"time":60000,"type":0},{"id":1,"sLen":0,"time":60294.1176470588,"type":0},{"id":2,"sLen":0,"time":60441.1764705882,"type":0},{"id":0,"sLen":0,"time":60588.2352941176,"type":0},{"id":1,"sLen":0,"time":60808.8235294117,"type":0},{"id":3,"sLen":0,"time":61029.4117647059,"type":0},{"id":2,"sLen":443.999999999993,"time":61176.4705882353,"type":0},{"id":1,"sLen":0,"time":61764.7058823529,"type":0},{"id":0,"sLen":0,"time":61911.7647058823,"type":0},{"id":2,"sLen":0,"time":62058.8235294117,"type":0},{"id":1,"sLen":0,"time":62205.8823529412,"type":0},{"id":3,"sLen":0,"time":62352.9411764706,"type":0},{"id":1,"sLen":0,"time":62500,"type":0},{"id":0,"sLen":0,"time":62647.0588235294,"type":0},{"id":2,"sLen":0,"time":62794.1176470588,"type":0},{"id":1,"sLen":0,"time":62941.1764705882,"type":0},{"id":2,"sLen":0,"time":63088.2352941176,"type":0},{"id":3,"sLen":0,"time":63161.7647058823,"type":0},{"id":1,"sLen":0,"time":63235.294117647,"type":0},{"id":2,"sLen":0,"time":63382.3529411765,"type":0},{"id":0,"sLen":444,"time":63529.4117647059,"type":0},{"id":1,"sLen":0,"time":64117.6470588235,"type":0},{"id":3,"sLen":0,"time":64264.7058823529,"type":0},{"id":1,"sLen":0,"time":64411.7647058823,"type":0},{"id":2,"sLen":0,"time":64558.8235294117,"type":0},{"id":0,"sLen":0,"time":64705.8823529412,"type":0},{"id":0,"sLen":0,"time":65000,"type":0},{"id":1,"sLen":0,"time":65294.1176470588,"type":0},{"id":2,"sLen":0,"time":65441.1764705882,"type":0},{"id":3,"sLen":0,"time":65514.7058823529,"type":0},{"id":1,"sLen":0,"time":65588.2352941176,"type":0},{"id":0,"sLen":0,"time":65735.294117647,"type":0},{"id":2,"sLen":0,"time":65808.8235294117,"type":0},{"id":3,"sLen":0,"time":66176.4705882353,"type":0},{"id":2,"sLen":0,"time":66323.5294117647,"type":0},{"id":1,"sLen":0,"time":66470.5882352941,"type":0},{"id":2,"sLen":0,"time":66617.6470588235,"type":0},{"id":0,"sLen":0,"time":66764.7058823529,"type":0},{"id":1,"sLen":0,"time":66911.7647058823,"type":0},{"id":3,"sLen":0,"time":67058.8235294118,"type":0},{"id":0,"sLen":0,"time":67205.8823529412,"type":0},{"id":2,"sLen":0,"time":67352.9411764706,"type":0},{"id":3,"sLen":0,"time":67500,"type":0},{"id":1,"sLen":0,"time":67647.0588235294,"type":0},{"id":2,"sLen":0,"time":67794.1176470588,"type":0},{"id":0,"sLen":148,"time":67941.1764705882,"type":0},{"id":1,"sLen":0,"time":68529.4117647059,"type":0},{"id":3,"sLen":0,"time":68676.4705882353,"type":0},{"id":2,"sLen":0,"time":68823.5294117647,"type":0},{"id":0,"sLen":0,"time":68970.5882352941,"type":0},{"id":1,"sLen":0,"time":69117.6470588235,"type":0},{"id":3,"sLen":0,"time":69264.7058823529,"type":0},{"id":1,"sLen":0,"time":69411.7647058823,"type":0},{"id":2,"sLen":0,"time":69411.7647058823,"type":0},{"id":0,"sLen":0,"time":69558.8235294117,"type":0},{"id":1,"sLen":0,"time":69705.8823529412,"type":0},{"id":3,"sLen":0,"time":69852.9411764706,"type":0},{"id":2,"sLen":0,"time":70000,"type":0},{"id":0,"sLen":0,"time":70147.0588235294,"type":0},{"id":1,"sLen":0,"time":70294.1176470588,"type":0},{"id":3,"sLen":0,"time":70441.1764705882,"type":0},{"id":2,"sLen":148,"time":70588.2352941176,"type":0},{"id":2,"sLen":0,"time":75588.2352941176,"type":0},{"id":1,"sLen":0,"time":75735.294117647,"type":0},{"id":3,"sLen":0,"time":75882.3529411765,"type":0},{"id":3,"sLen":296,"time":76176.4705882353,"type":0},{"id":1,"sLen":0,"time":76764.7058823529,"type":0},{"id":2,"sLen":0,"time":76911.7647058823,"type":0},{"id":0,"sLen":0,"time":77058.8235294117,"type":0},{"id":1,"sLen":0,"time":77205.8823529412,"type":0},{"id":2,"sLen":0,"time":77352.9411764706,"type":0},{"id":3,"sLen":444,"time":77352.9411764706,"type":0},{"id":0,"sLen":0,"time":77941.1764705882,"type":0},{"id":1,"sLen":0,"time":78088.2352941176,"type":0},{"id":2,"sLen":0,"time":78235.294117647,"type":0},{"id":2,"sLen":296,"time":78529.4117647059,"type":0},{"id":0,"sLen":0,"time":79117.6470588235,"type":0},{"id":3,"sLen":0,"time":79264.7058823529,"type":0},{"id":1,"sLen":0,"time":79411.7647058823,"type":0},{"id":2,"sLen":0,"time":79558.8235294117,"type":0},{"id":0,"sLen":443.999999999869,"time":79705.8823529412,"type":0}],"position":"dad","strumScale":1,"visible":false,"type":0,"characters":["gangsta"],"strumPos":[0,50],"strumLinePos":0.25,"vocalsSuffix":"GANGSTA"},{"notes":[{"id":1,"sLen":0,"time":14411.7647058824,"type":0},{"id":3,"sLen":0,"time":14558.8235294118,"type":0},{"id":1,"sLen":0,"time":14705.8823529412,"type":0},{"id":2,"sLen":0,"time":14852.9411764706,"type":0},{"id":0,"sLen":0,"time":15000,"type":0},{"id":1,"sLen":0,"time":15147.0588235294,"type":0},{"id":3,"sLen":0,"time":15294.1176470588,"type":0},{"id":1,"sLen":0,"time":15441.1764705882,"type":0},{"id":2,"sLen":0,"time":15588.2352941176,"type":0},{"id":0,"sLen":0,"time":15735.2941176471,"type":0},{"id":1,"sLen":0,"time":15882.3529411765,"type":0},{"id":3,"sLen":0,"time":16029.4117647059,"type":0},{"id":1,"sLen":0,"time":16176.4705882353,"type":0},{"id":2,"sLen":148,"time":16176.4705882353,"type":0},{"id":1,"sLen":0,"time":16764.7058823529,"type":0},{"id":3,"sLen":0,"time":16911.7647058823,"type":0},{"id":1,"sLen":0,"time":17058.8235294118,"type":0},{"id":2,"sLen":0,"time":17205.8823529412,"type":0},{"id":0,"sLen":0,"time":17352.9411764706,"type":0},{"id":0,"sLen":0,"time":17500,"type":0},{"id":2,"sLen":0,"time":17647.0588235294,"type":0},{"id":1,"sLen":0,"time":17794.1176470588,"type":0},{"id":3,"sLen":0,"time":17941.1764705882,"type":0},{"id":1,"sLen":0,"time":18088.2352941176,"type":0},{"id":2,"sLen":0,"time":18235.2941176471,"type":0},{"id":1,"sLen":0,"time":18382.3529411765,"type":0},{"id":0,"sLen":0,"time":18529.4117647059,"type":0},{"id":2,"sLen":0,"time":18676.4705882353,"type":0},{"id":1,"sLen":148,"time":18823.5294117647,"type":1},{"id":3,"sLen":0,"time":23823.5294117647,"type":0},{"id":0,"sLen":0,"time":23970.5882352941,"type":0},{"id":1,"sLen":0,"time":24117.6470588235,"type":0},{"id":1,"sLen":444,"time":24411.7647058823,"type":0},{"id":2,"sLen":0,"time":24411.7647058823,"type":0},{"id":3,"sLen":0,"time":25000,"type":0},{"id":0,"sLen":0,"time":25147.0588235294,"type":0},{"id":2,"sLen":0,"time":25294.1176470588,"type":0},{"id":3,"sLen":0,"time":25441.1764705882,"type":0},{"id":1,"sLen":445.000000000018,"time":25588.2352941176,"type":0},{"id":0,"sLen":0,"time":26176.4705882353,"type":0},{"id":3,"sLen":0,"time":26323.5294117647,"type":0},{"id":1,"sLen":0,"time":26470.5882352941,"type":0},{"id":2,"sLen":0,"time":26764.7058823529,"type":0},{"id":1,"sLen":0,"time":26911.7647058823,"type":0},{"id":3,"sLen":0,"time":27058.8235294118,"type":0},{"id":1,"sLen":0,"time":27205.8823529412,"type":0},{"id":0,"sLen":0,"time":27352.9411764706,"type":0},{"id":2,"sLen":0,"time":27500,"type":0},{"id":1,"sLen":0,"time":27647.0588235294,"type":0},{"id":3,"sLen":0,"time":27794.1176470588,"type":0},{"id":1,"sLen":0,"time":27941.1764705882,"type":0},{"id":0,"sLen":0,"time":28088.2352941176,"type":0},{"id":3,"sLen":0,"time":29411.7647058823,"type":0},{"id":0,"sLen":0,"time":29558.8235294118,"type":0},{"id":1,"sLen":0,"time":29705.8823529412,"type":0},{"id":1,"sLen":0,"time":29852.9411764706,"type":0},{"id":2,"sLen":0,"time":30000,"type":0},{"id":1,"sLen":0,"time":30147.0588235294,"type":0},{"id":3,"sLen":0,"time":30294.1176470588,"type":0},{"id":2,"sLen":0,"time":30441.1764705882,"type":0},{"id":1,"sLen":0,"time":31470.5882352941,"type":0},{"id":1,"sLen":0,"time":31617.6470588235,"type":0},{"id":2,"sLen":0,"time":31764.7058823529,"type":0},{"id":0,"sLen":0,"time":31911.7647058823,"type":0},{"id":1,"sLen":0,"time":32058.8235294118,"type":0},{"id":3,"sLen":0,"time":32205.8823529412,"type":0},{"id":1,"sLen":296,"time":32352.9411764706,"type":1},{"id":2,"sLen":0,"time":32352.9411764706,"type":1},{"id":0,"sLen":0,"time":32647.0588235294,"type":0},{"id":1,"sLen":0,"time":33970.5882352941,"type":0},{"id":0,"sLen":0,"time":34117.6470588235,"type":0},{"id":2,"sLen":0,"time":34264.7058823529,"type":0},{"id":1,"sLen":0,"time":34411.7647058823,"type":0},{"id":3,"sLen":0,"time":34558.8235294118,"type":0},{"id":1,"sLen":0,"time":34705.8823529412,"type":0},{"id":1,"sLen":0,"time":34852.9411764706,"type":0},{"id":0,"sLen":0,"time":35000,"type":0},{"id":2,"sLen":0,"time":35147.0588235294,"type":0},{"id":1,"sLen":0,"time":36176.4705882353,"type":0},{"id":2,"sLen":0,"time":36323.5294117647,"type":0},{"id":0,"sLen":0,"time":36470.5882352941,"type":0},{"id":1,"sLen":0,"time":36617.6470588235,"type":0},{"id":3,"sLen":0,"time":36764.7058823529,"type":0},{"id":1,"sLen":0,"time":36911.7647058823,"type":0},{"id":2,"sLen":148,"time":37058.8235294118,"type":0},{"id":0,"sLen":0,"time":37352.9411764706,"type":0},{"id":2,"sLen":0,"time":37500,"type":0},{"id":1,"sLen":0,"time":42647.0588235294,"type":0},{"id":1,"sLen":0,"time":43235.294117647,"type":0},{"id":2,"sLen":0,"time":43382.3529411765,"type":0},{"id":0,"sLen":0,"time":43529.4117647059,"type":0},{"id":1,"sLen":0,"time":43676.4705882353,"type":0},{"id":3,"sLen":0,"time":43823.5294117647,"type":0},{"id":1,"sLen":0,"time":43970.5882352941,"type":0},{"id":0,"sLen":0,"time":44117.6470588235,"type":0},{"id":2,"sLen":0,"time":44264.7058823529,"type":0},{"id":1,"sLen":0,"time":44411.7647058823,"type":0},{"id":3,"sLen":0,"time":44558.8235294118,"type":0},{"id":1,"sLen":148.000000000007,"time":44705.8823529412,"type":0},{"id":2,"sLen":0,"time":44705.8823529412,"type":0},{"id":0,"sLen":0,"time":45000,"type":0},{"id":1,"sLen":0,"time":45147.0588235294,"type":0},{"id":3,"sLen":0,"time":45294.1176470588,"type":0},{"id":2,"sLen":0,"time":45441.1764705882,"type":0},{"id":0,"sLen":0,"time":45588.2352941176,"type":0},{"id":2,"sLen":0,"time":45735.294117647,"type":0},{"id":1,"sLen":0,"time":45882.3529411765,"type":0},{"id":3,"sLen":0,"time":46176.4705882353,"type":0},{"id":0,"sLen":0,"time":46323.5294117647,"type":0},{"id":2,"sLen":0,"time":46470.5882352941,"type":0},{"id":3,"sLen":0,"time":46617.6470588235,"type":0},{"id":1,"sLen":0,"time":46764.7058823529,"type":0},{"id":2,"sLen":0,"time":46911.7647058823,"type":0},{"id":3,"sLen":0,"time":47058.8235294118,"type":0},{"id":3,"sLen":0,"time":47205.8823529412,"type":0},{"id":2,"sLen":0,"time":47352.9411764706,"type":0},{"id":1,"sLen":148,"time":47500,"type":0},{"id":2,"sLen":0,"time":47794.1176470588,"type":0},{"id":3,"sLen":0,"time":47941.1764705882,"type":0},{"id":1,"sLen":0,"time":48088.2352941176,"type":0},{"id":2,"sLen":0,"time":48235.294117647,"type":0},{"id":0,"sLen":0,"time":48382.3529411765,"type":0},{"id":1,"sLen":0,"time":48529.4117647059,"type":0},{"id":3,"sLen":0,"time":48676.4705882353,"type":0},{"id":1,"sLen":0,"time":48823.5294117647,"type":0},{"id":2,"sLen":0,"time":48970.5882352941,"type":0},{"id":0,"sLen":0,"time":49117.6470588235,"type":0},{"id":2,"sLen":0,"time":49264.7058823529,"type":0},{"id":3,"sLen":0,"time":49411.7647058823,"type":0},{"id":0,"sLen":0,"time":49558.8235294118,"type":0},{"id":2,"sLen":0,"time":49705.8823529412,"type":0},{"id":3,"sLen":0,"time":49852.9411764706,"type":0},{"id":1,"sLen":0,"time":50000,"type":0},{"id":2,"sLen":0,"time":50294.1176470588,"type":0},{"id":0,"sLen":0,"time":50441.1764705882,"type":0},{"id":1,"sLen":0,"time":50588.2352941176,"type":0},{"id":2,"sLen":0,"time":50882.3529411765,"type":0},{"id":1,"sLen":0,"time":51029.4117647059,"type":0},{"id":3,"sLen":0,"time":51176.4705882353,"type":0},{"id":2,"sLen":0,"time":51397.0588235294,"type":0},{"id":1,"sLen":0,"time":51470.5882352941,"type":0},{"id":0,"sLen":0,"time":51617.6470588235,"type":0},{"id":3,"sLen":444,"time":51764.7058823529,"type":0},{"id":1,"sLen":0,"time":52352.9411764706,"type":0},{"id":1,"sLen":0,"time":52500,"type":0},{"id":2,"sLen":0,"time":52647.0588235294,"type":0},{"id":0,"sLen":0,"time":52794.1176470588,"type":0},{"id":2,"sLen":0,"time":52941.1764705882,"type":0},{"id":3,"sLen":0,"time":53088.2352941176,"type":0},{"id":1,"sLen":0,"time":53235.294117647,"type":0},{"id":0,"sLen":0,"time":53382.3529411765,"type":0},{"id":2,"sLen":0,"time":53529.4117647059,"type":0},{"id":1,"sLen":0,"time":53676.4705882353,"type":0},{"id":3,"sLen":0,"time":53750,"type":0},{"id":2,"sLen":0,"time":53823.5294117647,"type":0},{"id":0,"sLen":0,"time":53970.5882352941,"type":0},{"id":1,"sLen":444,"time":54117.6470588235,"type":0},{"id":2,"sLen":0,"time":54705.8823529412,"type":0},{"id":0,"sLen":0,"time":54852.9411764706,"type":0},{"id":1,"sLen":0,"time":55000,"type":0},{"id":3,"sLen":0,"time":55147.0588235294,"type":0},{"id":1,"sLen":0,"time":55294.1176470588,"type":0},{"id":2,"sLen":0,"time":55294.1176470588,"type":0},{"id":0,"sLen":0,"time":55588.2352941176,"type":0},{"id":2,"sLen":0,"time":55882.3529411765,"type":0},{"id":3,"sLen":0,"time":56029.4117647059,"type":0},{"id":1,"sLen":0,"time":56102.9411764706,"type":0},{"id":0,"sLen":0,"time":56176.4705882353,"type":0},{"id":2,"sLen":0,"time":56323.5294117647,"type":0},{"id":1,"sLen":0,"time":56397.0588235294,"type":0},{"id":1,"sLen":0,"time":70882.3529411765,"type":0},{"id":3,"sLen":0,"time":71029.4117647059,"type":0},{"id":1,"sLen":0,"time":71176.4705882353,"type":0},{"id":2,"sLen":0,"time":71323.5294117647,"type":0},{"id":0,"sLen":0,"time":71470.5882352941,"type":0},{"id":0,"sLen":0,"time":71617.6470588235,"type":0},{"id":1,"sLen":0,"time":71764.7058823529,"type":0},{"id":3,"sLen":0,"time":71911.7647058823,"type":0},{"id":2,"sLen":0,"time":72058.8235294117,"type":0},{"id":0,"sLen":0,"time":72205.8823529412,"type":0},{"id":1,"sLen":0,"time":72352.9411764706,"type":0},{"id":3,"sLen":0,"time":72500,"type":0},{"id":1,"sLen":0,"time":72647.0588235294,"type":0},{"id":2,"sLen":148,"time":72647.0588235294,"type":0},{"id":0,"sLen":0,"time":73235.294117647,"type":0},{"id":2,"sLen":0,"time":73382.3529411765,"type":0},{"id":3,"sLen":0,"time":73529.4117647059,"type":0},{"id":1,"sLen":0,"time":73676.4705882353,"type":0},{"id":2,"sLen":0,"time":73823.5294117647,"type":0},{"id":0,"sLen":0,"time":73970.5882352941,"type":0},{"id":3,"sLen":0,"time":74117.6470588235,"type":0},{"id":1,"sLen":0,"time":74264.7058823529,"type":0},{"id":2,"sLen":0,"time":74411.7647058823,"type":0},{"id":0,"sLen":0,"time":74558.8235294117,"type":0},{"id":1,"sLen":0,"time":74705.8823529412,"type":0},{"id":3,"sLen":0,"time":74852.9411764706,"type":0},{"id":1,"sLen":0,"time":75000,"type":0},{"id":2,"sLen":0,"time":75147.0588235294,"type":0},{"id":0,"sLen":148,"time":75294.1176470588,"type":0},{"id":1,"sLen":0,"time":80294.1176470588,"type":0},{"id":1,"sLen":0,"time":80441.1764705882,"type":0},{"id":3,"sLen":0,"time":80588.2352941176,"type":0},{"id":2,"sLen":296,"time":80882.3529411765,"type":0},{"id":0,"sLen":0,"time":81470.5882352941,"type":0},{"id":2,"sLen":0,"time":81617.6470588235,"type":0},{"id":3,"sLen":0,"time":81764.7058823529,"type":0},{"id":0,"sLen":0,"time":81911.7647058823,"type":0},{"id":1,"sLen":444,"time":82058.8235294117,"type":0},{"id":3,"sLen":0,"time":82647.0588235294,"type":0},{"id":3,"sLen":0,"time":82794.1176470588,"type":0},{"id":2,"sLen":0,"time":82941.1764705882,"type":0},{"id":2,"sLen":0,"time":83235.294117647,"type":0},{"id":1,"sLen":0,"time":83382.3529411765,"type":0},{"id":3,"sLen":0,"time":83529.4117647059,"type":0},{"id":0,"sLen":0,"time":83676.4705882353,"type":0},{"id":2,"sLen":0,"time":83823.5294117647,"type":0},{"id":3,"sLen":0,"time":83970.5882352941,"type":0},{"id":1,"sLen":0,"time":84117.6470588235,"type":0},{"id":2,"sLen":0,"time":84264.7058823529,"type":0},{"id":0,"sLen":0,"time":84411.7647058823,"type":0},{"id":1,"sLen":0,"time":84558.8235294117,"type":0}],"position":"boyfriend","strumScale":1,"visible":true,"type":1,"characters":["pico-djset"],"strumPos":[0,50],"strumLinePos":0.5,"vocalsSuffix":"PICO"},{"notes":[],"visible":false,"strumPos":[0,50],"position":"girlfriend","strumScale":1,"vocalsSuffix":"","strumLinePos":0.25,"type":2,"characters":["ravergirl"]}],"stage":"discoroom","noteTypes":["No Anim Note"]}